This file is a merged representation of the entire codebase, combined into a single document by Repomix.

<file_summary>
This section contains a summary of this file.

<purpose>
This file contains a packed representation of the entire repository's contents.
It is designed to be easily consumable by AI systems for analysis, code review,
or other automated processes.
</purpose>

<file_format>
The content is organized as follows:
1. This summary section
2. Repository information
3. Directory structure
4. Repository files (if enabled)
5. Multiple file entries, each consisting of:
  - File path as an attribute
  - Full contents of the file
</file_format>

<usage_guidelines>
- This file should be treated as read-only. Any changes should be made to the
  original repository files, not this packed version.
- When processing this file, use the file path to distinguish
  between different files in the repository.
- Be aware that this file may contain sensitive information. Handle it with
  the same level of security as you would the original repository.
</usage_guidelines>

<notes>
- Some files may have been excluded based on .gitignore rules and Repomix's configuration
- Binary files are not included in this packed representation. Please refer to the Repository Structure section for a complete list of file paths, including binary files
- Files matching patterns in .gitignore are excluded
- Files matching default ignore patterns are excluded
- Files are sorted by Git change count (files with more changes are at the bottom)
</notes>

</file_summary>

<directory_structure>
.gitignore
eslint.config.js
index.html
package.json
public/favicon.svg
public/icons.svg
README.md
src/App.css
src/App.tsx
src/assets/Logo.svg
src/assets/menu.svg
src/components/Header/Header.tsx
src/components/Header/MobileMenu.tsx
src/components/icons/LogoIcon.tsx
src/components/icons/MenuIcon.tsx
src/index.css
src/main.tsx
tsconfig.app.json
tsconfig.json
tsconfig.node.json
vite.config.ts
</directory_structure>

<files>
This section contains the contents of the repository's files.

<file path="src/assets/Logo.svg">
<svg width="35" height="34" viewBox="0 0 35 34" fill="none" xmlns="http://www.w3.org/2000/svg">
<g clip-path="url(#clip0_44_745)">
<path d="M13.2283 16.5279C13.2283 17.5718 12.8129 18.5714 12.0752 19.3089L6.71443 24.6687C6.6244 24.7587 6.53279 24.8439 6.43486 24.9229C6.20109 25.1171 5.94679 25.2798 5.68144 25.4109C5.13178 25.6841 4.53157 25.8199 3.93294 25.8199C2.9268 25.8199 1.91908 25.4361 1.15145 24.6671C-0.383817 23.1321 -0.383817 20.6417 1.15145 19.1052L3.72918 16.5279L1.15145 13.9491C-0.383817 12.4142 -0.383817 9.92379 1.15145 8.38724C2.37556 7.16337 4.21093 6.91386 5.68144 7.64502C5.94995 7.77767 6.20583 7.94191 6.44276 8.13772C6.53595 8.21668 6.62756 8.2988 6.71443 8.38566L6.93082 8.60201L12.0752 13.7454C12.8144 14.4845 13.2283 15.4857 13.2283 16.5279Z" fill="#27272A"/>
<path d="M13.2282 16.5279C13.2282 17.5718 12.8128 18.5714 12.0752 19.3089L6.71437 24.6687C6.62434 24.7587 6.53273 24.8439 6.4348 24.9229C6.20103 25.1171 5.94673 25.2798 5.68138 25.4109C5.30704 25.2261 4.95797 24.9782 4.64681 24.6671C3.11154 23.1321 3.11154 20.6417 4.64681 19.1052L7.22454 16.5279L4.64839 13.9491C3.11312 12.4142 3.11312 9.92379 4.64839 8.38724C4.95955 8.07614 5.30862 7.82978 5.68138 7.64502C5.94989 7.77767 6.20577 7.94191 6.4427 8.13773C6.53589 8.21668 6.6275 8.2988 6.71437 8.38566L6.93076 8.60201L12.0752 13.7454C12.8144 14.4845 13.2282 15.4857 13.2282 16.5279Z" fill="#27272A"/>
<path d="M34.9998 16.5278C34.9998 25.6413 27.5841 33.0555 18.4689 33.0555H10.5793C8.507 33.0555 6.80746 31.4527 6.65741 29.4171C6.64793 29.3208 6.64478 29.2229 6.64478 29.1218C6.64478 26.9504 8.40591 25.188 10.5793 25.188H18.4704C23.2468 25.188 27.134 21.3032 27.134 16.5262C27.134 11.7507 23.2468 7.86435 18.4704 7.86435H10.5793C8.40749 7.86435 6.64478 6.10356 6.64478 3.9306C6.64478 3.83111 6.64793 3.73162 6.65741 3.63529C6.80746 1.60287 8.50542 0 10.5793 0H18.4704C27.5857 0 34.9998 7.41428 34.9998 16.5278Z" fill="#27272A"/>
<path d="M6.93069 8.6054C6.75221 8.46959 6.58794 8.31167 6.44263 8.14111C6.53582 8.22007 6.62743 8.30219 6.7143 8.38905L6.93069 8.6054Z" fill="#27272A"/>
<path d="M6.71438 24.6686C6.62435 24.7586 6.53274 24.8439 6.43481 24.9228C6.58487 24.7444 6.75545 24.5833 6.93867 24.4443L6.71438 24.6686Z" fill="#27272A"/>
<path d="M29.3469 16.528C29.3469 24.1444 23.1506 30.338 15.5343 30.338H8.93831C8.05064 30.338 7.24826 29.9874 6.65595 29.4173C6.64647 29.321 6.64331 29.2231 6.64331 29.122C6.64331 26.9506 8.40445 25.1882 10.5778 25.1882H18.469C23.2454 25.1882 27.1325 21.3035 27.1325 16.5264C27.1325 11.7509 23.2454 7.86457 18.469 7.86457H10.5794C8.4076 7.86457 6.64489 6.10378 6.64489 3.93082C6.64489 3.83133 6.64805 3.73184 6.65753 3.63551C7.24984 3.06542 8.05222 2.71484 8.93989 2.71484H15.5343C23.1506 2.718 29.3469 8.91157 29.3469 16.528Z" fill="#27272A"/>
</g>
<defs>
<clipPath id="clip0_44_745">
<rect width="35" height="33.0555" fill="white"/>
</clipPath>
</defs>
</svg>
</file>

<file path="src/assets/menu.svg">
<svg width="32" height="32" viewBox="0 0 32 32" fill="none" xmlns="http://www.w3.org/2000/svg">
<path fill-rule="evenodd" clip-rule="evenodd" d="M4.80005 7.9999C4.80005 7.57556 4.96862 7.16859 5.26868 6.86853C5.56874 6.56847 5.9757 6.3999 6.40005 6.3999H25.6C26.0244 6.3999 26.4314 6.56847 26.7314 6.86853C27.0315 7.16859 27.2 7.57556 27.2 7.9999C27.2 8.42425 27.0315 8.83121 26.7314 9.13127C26.4314 9.43133 26.0244 9.5999 25.6 9.5999H6.40005C5.9757 9.5999 5.56874 9.43133 5.26868 9.13127C4.96862 8.83121 4.80005 8.42425 4.80005 7.9999ZM4.80005 15.9999C4.80005 15.5756 4.96862 15.1686 5.26868 14.8685C5.56874 14.5685 5.9757 14.3999 6.40005 14.3999H25.6C26.0244 14.3999 26.4314 14.5685 26.7314 14.8685C27.0315 15.1686 27.2 15.5756 27.2 15.9999C27.2 16.4242 27.0315 16.8312 26.7314 17.1313C26.4314 17.4313 26.0244 17.5999 25.6 17.5999H6.40005C5.9757 17.5999 5.56874 17.4313 5.26868 17.1313C4.96862 16.8312 4.80005 16.4242 4.80005 15.9999ZM4.80005 23.9999C4.80005 23.5756 4.96862 23.1686 5.26868 22.8685C5.56874 22.5685 5.9757 22.3999 6.40005 22.3999H25.6C26.0244 22.3999 26.4314 22.5685 26.7314 22.8685C27.0315 23.1686 27.2 23.5756 27.2 23.9999C27.2 24.4242 27.0315 24.8312 26.7314 25.1313C26.4314 25.4313 26.0244 25.5999 25.6 25.5999H6.40005C5.9757 25.5999 5.56874 25.4313 5.26868 25.1313C4.96862 24.8312 4.80005 24.4242 4.80005 23.9999Z" fill="#27272A"/>
</svg>
</file>

<file path="src/components/Header/Header.tsx">
import {useState} from 'react';
import LogoIcon from '../icons/LogoIcon.tsx';
import MenuIcon from '../icons/MenuIcon.tsx';
import MobileMenu from './MobileMenu.tsx'

const Header = () => {
    const [isOpen, setIsOpen] = useState(false);

    const toggleOpen = () => setIsOpen(!isOpen);

    const close = () => setIsOpen(false);

    return (
        <>
            <header className="w-full bg-white py-4 px-4 flex justify-between items-center">
                <LogoIcon size={35} className="text-black"/>
                <button
                    onClick={toggleOpen}
                    className=""
                    aria-label="Toggle menu"
                >
                    <MenuIcon size={32} className="text-black"/>
                </button>
            </header>

            <MobileMenu isOpen={isOpen} onClose={close}/>
        </>
    )
        ;
};

export default Header;
</file>

<file path="src/components/Header/MobileMenu.tsx">
import MenuIcon from "../icons/MenuIcon.tsx";

interface MobileMenuProps {
    isOpen: boolean;
    onClose: () => void;
}

const MobileMenu: React.FC<MobileMenuProps> = ({isOpen, onClose}) => {
    return (
        <>
            <div
                className={`fixed inset-0 bg-black/65 transition-opacity duration-300 z-40 ${
                    isOpen ? 'opacity-100 visible' : 'opacity-0 invisible'
                }`}
                onClick={onClose}
            />

            <div
                className={`fixed top-0 right-0 h-full w-64 bg-white z-50 transition-transform duration-300 ease-in-out ${
                    isOpen ? 'translate-x-0' : 'translate-x-full'
                }`}
            >
                <button
                    onClick={onClose}
                    className="absolute top-4 right-4 p-2 transition-colors"
                >
                    <MenuIcon size={32} className="text-black"/>
                </button>

                <div className="pt-20 px-6">
                    <nav className="flex flex-col space-y-6">
                        <a href="#"
                           className="text-body-2 font-medium text-grey-dark">
                            Main
                        </a>
                        <a href="#"
                           className="text-body-2 font-medium text-grey-dark">
                            About
                        </a>
                        <a href="#"
                           className="text-body-2 font-medium text-grey-dark">
                            Get in touch
                        </a>
                    </nav>
                </div>
            </div>
        </>
    );
};

export default MobileMenu;
</file>

<file path="src/components/icons/LogoIcon.tsx">
interface LogoIconProps {
    className?: string;
    size?: number;
}

const LogoIcon: React.FC<LogoIconProps> = ({
                                               className = '',
                                               size = 35
                                           }) => {
    return (
        <svg
            width={size}
            height={size}
            viewBox="0 0 35 34"
            fill="none"
            xmlns="http://www.w3.org/2000/svg"
            className={className}
        >
            <path
                d="M13.2283 16.5279C13.2283 17.5718 12.8129 18.5714 12.0752 19.3089L6.71443 24.6687C6.6244 24.7587 6.53279 24.8439 6.43486 24.9229C6.20109 25.1171 5.94679 25.2798 5.68144 25.4109C5.13178 25.6841 4.53157 25.8199 3.93294 25.8199C2.9268 25.8199 1.91908 25.4361 1.15145 24.6671C-0.383817 23.1321 -0.383817 20.6417 1.15145 19.1052L3.72918 16.5279L1.15145 13.9491C-0.383817 12.4142 -0.383817 9.92379 1.15145 8.38724C2.37556 7.16337 4.21093 6.91386 5.68144 7.64502C5.94995 7.77767 6.20583 7.94191 6.44276 8.13772C6.53595 8.21668 6.62756 8.2988 6.71443 8.38566L6.93082 8.60201L12.0752 13.7454C12.8144 14.4845 13.2283 15.4857 13.2283 16.5279Z"
                fill="currentColor"
            />
            <path
                d="M13.2282 16.5279C13.2282 17.5718 12.8128 18.5714 12.0752 19.3089L6.71437 24.6687C6.62434 24.7587 6.53273 24.8439 6.4348 24.9229C6.20103 25.1171 5.94673 25.2798 5.68138 25.4109C5.30704 25.2261 4.95797 24.9782 4.64681 24.6671C3.11154 23.1321 3.11154 20.6417 4.64681 19.1052L7.22454 16.5279L4.64839 13.9491C3.11312 12.4142 3.11312 9.92379 4.64839 8.38724C4.95955 8.07614 5.30862 7.82978 5.68138 7.64502C5.94989 7.77767 6.20577 7.94191 6.4427 8.13773C6.53589 8.21668 6.6275 8.2988 6.71437 8.38566L6.93076 8.60201L12.0752 13.7454C12.8144 14.4845 13.2282 15.4857 13.2282 16.5279Z"
                fill="currentColor"
            />
            <path
                d="M34.9998 16.5278C34.9998 25.6413 27.5841 33.0555 18.4689 33.0555H10.5793C8.507 33.0555 6.80746 31.4527 6.65741 29.4171C6.64793 29.3208 6.64478 29.2229 6.64478 29.1218C6.64478 26.9504 8.40591 25.188 10.5793 25.188H18.4704C23.2468 25.188 27.134 21.3032 27.134 16.5262C27.134 11.7507 23.2468 7.86435 18.4704 7.86435H10.5793C8.40749 7.86435 6.64478 6.10356 6.64478 3.9306C6.64478 3.83111 6.64793 3.73162 6.65741 3.63529C6.80746 1.60287 8.50542 0 10.5793 0H18.4704C27.5857 0 34.9998 7.41428 34.9998 16.5278Z"
                fill="currentColor"
            />
            <path
                d="M6.93069 8.6054C6.75221 8.46959 6.58794 8.31167 6.44263 8.14111C6.53582 8.22007 6.62743 8.30219 6.7143 8.38905L6.93069 8.6054Z"
                fill="currentColor"
            />
            <path
                d="M6.71438 24.6686C6.62435 24.7586 6.53274 24.8439 6.43481 24.9228C6.58487 24.7444 6.75545 24.5833 6.93867 24.4443L6.71438 24.6686Z"
                fill="currentColor"
            />
            <path
                d="M29.3469 16.528C29.3469 24.1444 23.1506 30.338 15.5343 30.338H8.93831C8.05064 30.338 7.24826 29.9874 6.65595 29.4173C6.64647 29.321 6.64331 29.2231 6.64331 29.122C6.64331 26.9506 8.40445 25.1882 10.5778 25.1882H18.469C23.2454 25.1882 27.1325 21.3035 27.1325 16.5264C27.1325 11.7509 23.2454 7.86457 18.469 7.86457H10.5794C8.4076 7.86457 6.64489 6.10378 6.64489 3.93082C6.64489 3.83133 6.64805 3.73184 6.65753 3.63551C7.24984 3.06542 8.05222 2.71484 8.93989 2.71484H15.5343C23.1506 2.718 29.3469 8.91157 29.3469 16.528Z"
                fill="currentColor"
            />
        </svg>
    );
};

export default LogoIcon;
</file>

<file path="src/components/icons/MenuIcon.tsx">
interface MenuIconProps {
    className?: string;
    size?: number;
    onClick?: () => void;
}

const MenuIcon: React.FC<MenuIconProps> = ({
                                               className = '',
                                               size = 32,
                                               onClick
                                           }) => {
    return (
        <svg
            width={size}
            height={size}
            viewBox="0 0 32 32"
            fill="none"
            xmlns="http://www.w3.org/2000/svg"
            className={className}
            onClick={onClick}>

            <path fillRule="evenodd" clipRule="evenodd"
                  d="M4.80005 7.9999C4.80005 7.57556 4.96862 7.16859 5.26868 6.86853C5.56874 6.56847 5.9757 6.3999 6.40005 6.3999H25.6C26.0244 6.3999 26.4314 6.56847 26.7314 6.86853C27.0315 7.16859 27.2 7.57556 27.2 7.9999C27.2 8.42425 27.0315 8.83121 26.7314 9.13127C26.4314 9.43133 26.0244 9.5999 25.6 9.5999H6.40005C5.9757 9.5999 5.56874 9.43133 5.26868 9.13127C4.96862 8.83121 4.80005 8.42425 4.80005 7.9999ZM4.80005 15.9999C4.80005 15.5756 4.96862 15.1686 5.26868 14.8685C5.56874 14.5685 5.9757 14.3999 6.40005 14.3999H25.6C26.0244 14.3999 26.4314 14.5685 26.7314 14.8685C27.0315 15.1686 27.2 15.5756 27.2 15.9999C27.2 16.4242 27.0315 16.8312 26.7314 17.1313C26.4314 17.4313 26.0244 17.5999 25.6 17.5999H6.40005C5.9757 17.5999 5.56874 17.4313 5.26868 17.1313C4.96862 16.8312 4.80005 16.4242 4.80005 15.9999ZM4.80005 23.9999C4.80005 23.5756 4.96862 23.1686 5.26868 22.8685C5.56874 22.5685 5.9757 22.3999 6.40005 22.3999H25.6C26.0244 22.3999 26.4314 22.5685 26.7314 22.8685C27.0315 23.1686 27.2 23.5756 27.2 23.9999C27.2 24.4242 27.0315 24.8312 26.7314 25.1313C26.4314 25.4313 26.0244 25.5999 25.6 25.5999H6.40005C5.9757 25.5999 5.56874 25.4313 5.26868 25.1313C4.96862 24.8312 4.80005 24.4242 4.80005 23.9999Z"
                  fill="currentColor"/>
        </svg>

    );
};

export default MenuIcon;
</file>

<file path=".gitignore">
# Logs
logs
*.log
npm-debug.log*
yarn-debug.log*
yarn-error.log*
pnpm-debug.log*
lerna-debug.log*

node_modules
dist
dist-ssr
*.local

# Editor directories and files
.vscode/*
!.vscode/extensions.json
.idea
.DS_Store
*.suo
*.ntvs*
*.njsproj
*.sln
*.sw?
</file>

<file path="eslint.config.js">
import js from '@eslint/js'
import globals from 'globals'
import reactHooks from 'eslint-plugin-react-hooks'
import reactRefresh from 'eslint-plugin-react-refresh'
import tseslint from 'typescript-eslint'
import { defineConfig, globalIgnores } from 'eslint/config'

export default defineConfig([
  globalIgnores(['dist']),
  {
    files: ['**/*.{ts,tsx}'],
    extends: [
      js.configs.recommended,
      tseslint.configs.recommended,
      reactHooks.configs.flat.recommended,
      reactRefresh.configs.vite,
    ],
    languageOptions: {
      globals: globals.browser,
    },
  },
])
</file>

<file path="index.html">
<!doctype html>
<html lang="en">
  <head>
    <meta charset="UTF-8" />
    <link rel="icon" type="image/svg+xml" href="/favicon.svg" />
    <meta name="viewport" content="width=device-width, initial-scale=1.0" />
    <title>project1</title>
  </head>
  <body>
    <div id="root"></div>
    <script type="module" src="/src/main.tsx"></script>
  </body>
</html>
</file>

<file path="public/favicon.svg">
<svg xmlns="http://www.w3.org/2000/svg" width="48" height="46" fill="none" viewBox="0 0 48 46"><path fill="#863bff" d="M25.946 44.938c-.664.845-2.021.375-2.021-.698V33.937a2.26 2.26 0 0 0-2.262-2.262H10.287c-.92 0-1.456-1.04-.92-1.788l7.48-10.471c1.07-1.497 0-3.578-1.842-3.578H1.237c-.92 0-1.456-1.04-.92-1.788L10.013.474c.214-.297.556-.474.92-.474h28.894c.92 0 1.456 1.04.92 1.788l-7.48 10.471c-1.07 1.498 0 3.579 1.842 3.579h11.377c.943 0 1.473 1.088.89 1.83L25.947 44.94z" style="fill:#863bff;fill:color(display-p3 .5252 .23 1);fill-opacity:1"/><mask id="a" width="48" height="46" x="0" y="0" maskUnits="userSpaceOnUse" style="mask-type:alpha"><path fill="#000" d="M25.842 44.938c-.664.844-2.021.375-2.021-.698V33.937a2.26 2.26 0 0 0-2.262-2.262H10.183c-.92 0-1.456-1.04-.92-1.788l7.48-10.471c1.07-1.498 0-3.579-1.842-3.579H1.133c-.92 0-1.456-1.04-.92-1.787L9.91.473c.214-.297.556-.474.92-.474h28.894c.92 0 1.456 1.04.92 1.788l-7.48 10.471c-1.07 1.498 0 3.578 1.842 3.578h11.377c.943 0 1.473 1.088.89 1.832L25.843 44.94z" style="fill:#000;fill-opacity:1"/></mask><g mask="url(#a)"><g filter="url(#b)"><ellipse cx="5.508" cy="14.704" fill="#ede6ff" rx="5.508" ry="14.704" style="fill:#ede6ff;fill:color(display-p3 .9275 .9033 1);fill-opacity:1" transform="matrix(.00324 1 1 -.00324 -4.47 31.516)"/></g><g filter="url(#c)"><ellipse cx="10.399" cy="29.851" fill="#ede6ff" rx="10.399" ry="29.851" style="fill:#ede6ff;fill:color(display-p3 .9275 .9033 1);fill-opacity:1" transform="matrix(.00324 1 1 -.00324 -39.328 7.883)"/></g><g filter="url(#d)"><ellipse cx="5.508" cy="30.487" fill="#7e14ff" rx="5.508" ry="30.487" style="fill:#7e14ff;fill:color(display-p3 .4922 .0767 1);fill-opacity:1" transform="rotate(89.814 -25.913 -14.639)scale(1 -1)"/></g><g filter="url(#e)"><ellipse cx="5.508" cy="30.599" fill="#7e14ff" rx="5.508" ry="30.599" style="fill:#7e14ff;fill:color(display-p3 .4922 .0767 1);fill-opacity:1" transform="rotate(89.814 -32.644 -3.334)scale(1 -1)"/></g><g filter="url(#f)"><ellipse cx="5.508" cy="30.599" fill="#7e14ff" rx="5.508" ry="30.599" style="fill:#7e14ff;fill:color(display-p3 .4922 .0767 1);fill-opacity:1" transform="matrix(.00324 1 1 -.00324 -34.34 30.47)"/></g><g filter="url(#g)"><ellipse cx="14.072" cy="22.078" fill="#ede6ff" rx="14.072" ry="22.078" style="fill:#ede6ff;fill:color(display-p3 .9275 .9033 1);fill-opacity:1" transform="rotate(93.35 24.506 48.493)scale(-1 1)"/></g><g filter="url(#h)"><ellipse cx="3.47" cy="21.501" fill="#7e14ff" rx="3.47" ry="21.501" style="fill:#7e14ff;fill:color(display-p3 .4922 .0767 1);fill-opacity:1" transform="rotate(89.009 28.708 47.59)scale(-1 1)"/></g><g filter="url(#i)"><ellipse cx="3.47" cy="21.501" fill="#7e14ff" rx="3.47" ry="21.501" style="fill:#7e14ff;fill:color(display-p3 .4922 .0767 1);fill-opacity:1" transform="rotate(89.009 28.708 47.59)scale(-1 1)"/></g><g filter="url(#j)"><ellipse cx=".387" cy="8.972" fill="#7e14ff" rx="4.407" ry="29.108" style="fill:#7e14ff;fill:color(display-p3 .4922 .0767 1);fill-opacity:1" transform="rotate(39.51 .387 8.972)"/></g><g filter="url(#k)"><ellipse cx="47.523" cy="-6.092" fill="#7e14ff" rx="4.407" ry="29.108" style="fill:#7e14ff;fill:color(display-p3 .4922 .0767 1);fill-opacity:1" transform="rotate(37.892 47.523 -6.092)"/></g><g filter="url(#l)"><ellipse cx="41.412" cy="6.333" fill="#47bfff" rx="5.971" ry="9.665" style="fill:#47bfff;fill:color(display-p3 .2799 .748 1);fill-opacity:1" transform="rotate(37.892 41.412 6.333)"/></g><g filter="url(#m)"><ellipse cx="-1.879" cy="38.332" fill="#7e14ff" rx="4.407" ry="29.108" style="fill:#7e14ff;fill:color(display-p3 .4922 .0767 1);fill-opacity:1" transform="rotate(37.892 -1.88 38.332)"/></g><g filter="url(#n)"><ellipse cx="-1.879" cy="38.332" fill="#7e14ff" rx="4.407" ry="29.108" style="fill:#7e14ff;fill:color(display-p3 .4922 .0767 1);fill-opacity:1" transform="rotate(37.892 -1.88 38.332)"/></g><g filter="url(#o)"><ellipse cx="35.651" cy="29.907" fill="#7e14ff" rx="4.407" ry="29.108" style="fill:#7e14ff;fill:color(display-p3 .4922 .0767 1);fill-opacity:1" transform="rotate(37.892 35.651 29.907)"/></g><g filter="url(#p)"><ellipse cx="38.418" cy="32.4" fill="#47bfff" rx="5.971" ry="15.297" style="fill:#47bfff;fill:color(display-p3 .2799 .748 1);fill-opacity:1" transform="rotate(37.892 38.418 32.4)"/></g></g><defs><filter id="b" width="60.045" height="41.654" x="-19.77" y="16.149" color-interpolation-filters="sRGB" filterUnits="userSpaceOnUse"><feFlood flood-opacity="0" result="BackgroundImageFix"/><feBlend in="SourceGraphic" in2="BackgroundImageFix" result="shape"/><feGaussianBlur result="effect1_foregroundBlur_2002_17158" stdDeviation="7.659"/></filter><filter id="c" width="90.34" height="51.437" x="-54.613" y="-7.533" color-interpolation-filters="sRGB" filterUnits="userSpaceOnUse"><feFlood flood-opacity="0" result="BackgroundImageFix"/><feBlend in="SourceGraphic" in2="BackgroundImageFix" result="shape"/><feGaussianBlur result="effect1_foregroundBlur_2002_17158" stdDeviation="7.659"/></filter><filter id="d" width="79.355" height="29.4" x="-49.64" y="2.03" color-interpolation-filters="sRGB" filterUnits="userSpaceOnUse"><feFlood flood-opacity="0" result="BackgroundImageFix"/><feBlend in="SourceGraphic" in2="BackgroundImageFix" result="shape"/><feGaussianBlur result="effect1_foregroundBlur_2002_17158" stdDeviation="4.596"/></filter><filter id="e" width="79.579" height="29.4" x="-45.045" y="20.029" color-interpolation-filters="sRGB" filterUnits="userSpaceOnUse"><feFlood flood-opacity="0" result="BackgroundImageFix"/><feBlend in="SourceGraphic" in2="BackgroundImageFix" result="shape"/><feGaussianBlur result="effect1_foregroundBlur_2002_17158" stdDeviation="4.596"/></filter><filter id="f" width="79.579" height="29.4" x="-43.513" y="21.178" color-interpolation-filters="sRGB" filterUnits="userSpaceOnUse"><feFlood flood-opacity="0" result="BackgroundImageFix"/><feBlend in="SourceGraphic" in2="BackgroundImageFix" result="shape"/><feGaussianBlur result="effect1_foregroundBlur_2002_17158" stdDeviation="4.596"/></filter><filter id="g" width="74.749" height="58.852" x="15.756" y="-17.901" color-interpolation-filters="sRGB" filterUnits="userSpaceOnUse"><feFlood flood-opacity="0" result="BackgroundImageFix"/><feBlend in="SourceGraphic" in2="BackgroundImageFix" result="shape"/><feGaussianBlur result="effect1_foregroundBlur_2002_17158" stdDeviation="7.659"/></filter><filter id="h" width="61.377" height="25.362" x="23.548" y="2.284" color-interpolation-filters="sRGB" filterUnits="userSpaceOnUse"><feFlood flood-opacity="0" result="BackgroundImageFix"/><feBlend in="SourceGraphic" in2="BackgroundImageFix" result="shape"/><feGaussianBlur result="effect1_foregroundBlur_2002_17158" stdDeviation="4.596"/></filter><filter id="i" width="61.377" height="25.362" x="23.548" y="2.284" color-interpolation-filters="sRGB" filterUnits="userSpaceOnUse"><feFlood flood-opacity="0" result="BackgroundImageFix"/><feBlend in="SourceGraphic" in2="BackgroundImageFix" result="shape"/><feGaussianBlur result="effect1_foregroundBlur_2002_17158" stdDeviation="4.596"/></filter><filter id="j" width="56.045" height="63.649" x="-27.636" y="-22.853" color-interpolation-filters="sRGB" filterUnits="userSpaceOnUse"><feFlood flood-opacity="0" result="BackgroundImageFix"/><feBlend in="SourceGraphic" in2="BackgroundImageFix" result="shape"/><feGaussianBlur result="effect1_foregroundBlur_2002_17158" stdDeviation="4.596"/></filter><filter id="k" width="54.814" height="64.646" x="20.116" y="-38.415" color-interpolation-filters="sRGB" filterUnits="userSpaceOnUse"><feFlood flood-opacity="0" result="BackgroundImageFix"/><feBlend in="SourceGraphic" in2="BackgroundImageFix" result="shape"/><feGaussianBlur result="effect1_foregroundBlur_2002_17158" stdDeviation="4.596"/></filter><filter id="l" width="33.541" height="35.313" x="24.641" y="-11.323" color-interpolation-filters="sRGB" filterUnits="userSpaceOnUse"><feFlood flood-opacity="0" result="BackgroundImageFix"/><feBlend in="SourceGraphic" in2="BackgroundImageFix" result="shape"/><feGaussianBlur result="effect1_foregroundBlur_2002_17158" stdDeviation="4.596"/></filter><filter id="m" width="54.814" height="64.646" x="-29.286" y="6.009" color-interpolation-filters="sRGB" filterUnits="userSpaceOnUse"><feFlood flood-opacity="0" result="BackgroundImageFix"/><feBlend in="SourceGraphic" in2="BackgroundImageFix" result="shape"/><feGaussianBlur result="effect1_foregroundBlur_2002_17158" stdDeviation="4.596"/></filter><filter id="n" width="54.814" height="64.646" x="-29.286" y="6.009" color-interpolation-filters="sRGB" filterUnits="userSpaceOnUse"><feFlood flood-opacity="0" result="BackgroundImageFix"/><feBlend in="SourceGraphic" in2="BackgroundImageFix" result="shape"/><feGaussianBlur result="effect1_foregroundBlur_2002_17158" stdDeviation="4.596"/></filter><filter id="o" width="54.814" height="64.646" x="8.244" y="-2.416" color-interpolation-filters="sRGB" filterUnits="userSpaceOnUse"><feFlood flood-opacity="0" result="BackgroundImageFix"/><feBlend in="SourceGraphic" in2="BackgroundImageFix" result="shape"/><feGaussianBlur result="effect1_foregroundBlur_2002_17158" stdDeviation="4.596"/></filter><filter id="p" width="39.409" height="43.623" x="18.713" y="10.588" color-interpolation-filters="sRGB" filterUnits="userSpaceOnUse"><feFlood flood-opacity="0" result="BackgroundImageFix"/><feBlend in="SourceGraphic" in2="BackgroundImageFix" result="shape"/><feGaussianBlur result="effect1_foregroundBlur_2002_17158" stdDeviation="4.596"/></filter></defs></svg>
</file>

<file path="public/icons.svg">
<svg xmlns="http://www.w3.org/2000/svg">
  <symbol id="bluesky-icon" viewBox="0 0 16 17">
    <g clip-path="url(#bluesky-clip)"><path fill="#08060d" d="M7.75 7.735c-.693-1.348-2.58-3.86-4.334-5.097-1.68-1.187-2.32-.981-2.74-.79C.188 2.065.1 2.812.1 3.251s.241 3.602.398 4.13c.52 1.744 2.367 2.333 4.07 2.145-2.495.37-4.71 1.278-1.805 4.512 3.196 3.309 4.38-.71 4.987-2.746.608 2.036 1.307 5.91 4.93 2.746 2.72-2.746.747-4.143-1.747-4.512 1.702.189 3.55-.4 4.07-2.145.156-.528.397-3.691.397-4.13s-.088-1.186-.575-1.406c-.42-.19-1.06-.395-2.741.79-1.755 1.24-3.64 3.752-4.334 5.099"/></g>
    <defs><clipPath id="bluesky-clip"><path fill="#fff" d="M.1.85h15.3v15.3H.1z"/></clipPath></defs>
  </symbol>
  <symbol id="discord-icon" viewBox="0 0 20 19">
    <path fill="#08060d" d="M16.224 3.768a14.5 14.5 0 0 0-3.67-1.153c-.158.286-.343.67-.47.976a13.5 13.5 0 0 0-4.067 0c-.128-.306-.317-.69-.476-.976A14.4 14.4 0 0 0 3.868 3.77C1.546 7.28.916 10.703 1.231 14.077a14.7 14.7 0 0 0 4.5 2.306q.545-.748.965-1.587a9.5 9.5 0 0 1-1.518-.74q.191-.14.372-.293c2.927 1.369 6.107 1.369 8.999 0q.183.152.372.294-.723.437-1.52.74.418.838.963 1.588a14.6 14.6 0 0 0 4.504-2.308c.37-3.911-.63-7.302-2.644-10.309m-9.13 8.234c-.878 0-1.599-.82-1.599-1.82 0-.998.705-1.82 1.6-1.82.894 0 1.614.82 1.599 1.82.001 1-.705 1.82-1.6 1.82m5.91 0c-.878 0-1.599-.82-1.599-1.82 0-.998.705-1.82 1.6-1.82.893 0 1.614.82 1.599 1.82 0 1-.706 1.82-1.6 1.82"/>
  </symbol>
  <symbol id="documentation-icon" viewBox="0 0 21 20">
    <path fill="none" stroke="#aa3bff" stroke-linecap="round" stroke-linejoin="round" stroke-width="1.35" d="m15.5 13.333 1.533 1.322c.645.555.967.833.967 1.178s-.322.623-.967 1.179L15.5 18.333m-3.333-5-1.534 1.322c-.644.555-.966.833-.966 1.178s.322.623.966 1.179l1.534 1.321"/>
    <path fill="none" stroke="#aa3bff" stroke-linecap="round" stroke-linejoin="round" stroke-width="1.35" d="M17.167 10.836v-4.32c0-1.41 0-2.117-.224-2.68-.359-.906-1.118-1.621-2.08-1.96-.599-.21-1.349-.21-2.848-.21-2.623 0-3.935 0-4.983.369-1.684.591-3.013 1.842-3.641 3.428C3 6.449 3 7.684 3 10.154v2.122c0 2.558 0 3.838.706 4.726q.306.383.713.671c.76.536 1.79.64 3.581.66"/>
    <path fill="none" stroke="#aa3bff" stroke-linecap="round" stroke-linejoin="round" stroke-width="1.35" d="M3 10a2.78 2.78 0 0 1 2.778-2.778c.555 0 1.209.097 1.748-.047.48-.129.854-.503.982-.982.145-.54.048-1.194.048-1.749a2.78 2.78 0 0 1 2.777-2.777"/>
  </symbol>
  <symbol id="github-icon" viewBox="0 0 19 19">
    <path fill="#08060d" fill-rule="evenodd" d="M9.356 1.85C5.05 1.85 1.57 5.356 1.57 9.694a7.84 7.84 0 0 0 5.324 7.44c.387.079.528-.168.528-.376 0-.182-.013-.805-.013-1.454-2.165.467-2.616-.935-2.616-.935-.349-.91-.864-1.143-.864-1.143-.71-.48.051-.48.051-.48.787.051 1.2.805 1.2.805.695 1.194 1.817.857 2.268.649.064-.507.27-.857.49-1.052-1.728-.182-3.545-.857-3.545-3.87 0-.857.31-1.558.8-2.104-.078-.195-.349-1 .077-2.078 0 0 .657-.208 2.14.805a7.5 7.5 0 0 1 1.946-.26c.657 0 1.328.092 1.946.26 1.483-1.013 2.14-.805 2.14-.805.426 1.078.155 1.883.078 2.078.502.546.799 1.247.799 2.104 0 3.013-1.818 3.675-3.558 3.87.284.247.528.714.528 1.454 0 1.052-.012 1.896-.012 2.156 0 .208.142.455.528.377a7.84 7.84 0 0 0 5.324-7.441c.013-4.338-3.48-7.844-7.773-7.844" clip-rule="evenodd"/>
  </symbol>
  <symbol id="social-icon" viewBox="0 0 20 20">
    <path fill="none" stroke="#aa3bff" stroke-linecap="round" stroke-linejoin="round" stroke-width="1.35" d="M12.5 6.667a4.167 4.167 0 1 0-8.334 0 4.167 4.167 0 0 0 8.334 0"/>
    <path fill="none" stroke="#aa3bff" stroke-linecap="round" stroke-linejoin="round" stroke-width="1.35" d="M2.5 16.667a5.833 5.833 0 0 1 8.75-5.053m3.837.474.513 1.035c.07.144.257.282.414.309l.93.155c.596.1.736.536.307.965l-.723.73a.64.64 0 0 0-.152.531l.207.903c.164.715-.213.991-.84.618l-.872-.52a.63.63 0 0 0-.577 0l-.872.52c-.624.373-1.003.094-.84-.618l.207-.903a.64.64 0 0 0-.152-.532l-.723-.729c-.426-.43-.289-.864.306-.964l.93-.156a.64.64 0 0 0 .412-.31l.513-1.034c.28-.562.735-.562 1.012 0"/>
  </symbol>
  <symbol id="x-icon" viewBox="0 0 19 19">
    <path fill="#08060d" fill-rule="evenodd" d="M1.893 1.98c.052.072 1.245 1.769 2.653 3.77l2.892 4.114c.183.261.333.48.333.486s-.068.089-.152.183l-.522.593-.765.867-3.597 4.087c-.375.426-.734.834-.798.905a1 1 0 0 0-.118.148c0 .01.236.017.664.017h.663l.729-.83c.4-.457.796-.906.879-.999a692 692 0 0 0 1.794-2.038c.034-.037.301-.34.594-.675l.551-.624.345-.392a7 7 0 0 1 .34-.374c.006 0 .93 1.306 2.052 2.903l2.084 2.965.045.063h2.275c1.87 0 2.273-.003 2.266-.021-.008-.02-1.098-1.572-3.894-5.547-2.013-2.862-2.28-3.246-2.273-3.266.008-.019.282-.332 2.085-2.38l2-2.274 1.567-1.782c.022-.028-.016-.03-.65-.03h-.674l-.3.342a871 871 0 0 1-1.782 2.025c-.067.075-.405.458-.75.852a100 100 0 0 1-.803.91c-.148.172-.299.344-.99 1.127-.304.343-.32.358-.345.327-.015-.019-.904-1.282-1.976-2.808L6.365 1.85H1.8zm1.782.91 8.078 11.294c.772 1.08 1.413 1.973 1.425 1.984.016.017.241.02 1.05.017l1.03-.004-2.694-3.766L7.796 5.75 5.722 2.852l-1.039-.004-1.039-.004z" clip-rule="evenodd"/>
  </symbol>
</svg>
</file>

<file path="README.md">
# React + TypeScript + Vite

This template provides a minimal setup to get React working in Vite with HMR and some ESLint rules.

Currently, two official plugins are available:

- [@vitejs/plugin-react](https://github.com/vitejs/vite-plugin-react/blob/main/packages/plugin-react) uses [Oxc](https://oxc.rs)
- [@vitejs/plugin-react-swc](https://github.com/vitejs/vite-plugin-react/blob/main/packages/plugin-react-swc) uses [SWC](https://swc.rs/)

## React Compiler

The React Compiler is not enabled on this template because of its impact on dev & build performances. To add it, see [this documentation](https://react.dev/learn/react-compiler/installation).

## Expanding the ESLint configuration

If you are developing a production application, we recommend updating the configuration to enable type-aware lint rules:

```js
export default defineConfig([
  globalIgnores(['dist']),
  {
    files: ['**/*.{ts,tsx}'],
    extends: [
      // Other configs...

      // Remove tseslint.configs.recommended and replace with this
      tseslint.configs.recommendedTypeChecked,
      // Alternatively, use this for stricter rules
      tseslint.configs.strictTypeChecked,
      // Optionally, add this for stylistic rules
      tseslint.configs.stylisticTypeChecked,

      // Other configs...
    ],
    languageOptions: {
      parserOptions: {
        project: ['./tsconfig.node.json', './tsconfig.app.json'],
        tsconfigRootDir: import.meta.dirname,
      },
      // other options...
    },
  },
])

```

You can also install [eslint-plugin-react-x](https://github.com/Rel1cx/eslint-react/tree/main/packages/plugins/eslint-plugin-react-x) and [eslint-plugin-react-dom](https://github.com/Rel1cx/eslint-react/tree/main/packages/plugins/eslint-plugin-react-dom) for React-specific lint rules:

```js
// eslint.config.js
import reactX from 'eslint-plugin-react-x'
import reactDom from 'eslint-plugin-react-dom'

export default defineConfig([
  globalIgnores(['dist']),
  {
    files: ['**/*.{ts,tsx}'],
    extends: [
      // Other configs...
      // Enable lint rules for React
      reactX.configs['recommended-typescript'],
      // Enable lint rules for React DOM
      reactDom.configs.recommended,
    ],
    languageOptions: {
      parserOptions: {
        project: ['./tsconfig.node.json', './tsconfig.app.json'],
        tsconfigRootDir: import.meta.dirname,
      },
      // other options...
    },
  },
])

```
</file>

<file path="src/main.tsx">
import { StrictMode } from 'react'
import { createRoot } from 'react-dom/client'
import './index.css'
import App from './App.tsx'

createRoot(document.getElementById('root')!).render(
  <StrictMode>
    <App />
  </StrictMode>,
)
</file>

<file path="tsconfig.app.json">
{
  "compilerOptions": {
    "tsBuildInfoFile": "./node_modules/.tmp/tsconfig.app.tsbuildinfo",
    "target": "es2023",
    "lib": ["ES2023", "DOM"],
    "module": "esnext",
    "types": ["vite/client"],
    "allowArbitraryExtensions": true,
    "skipLibCheck": true,

    /* Bundler mode */
    "moduleResolution": "bundler",
    "allowImportingTsExtensions": true,
    "verbatimModuleSyntax": true,
    "moduleDetection": "force",
    "noEmit": true,
    "jsx": "react-jsx",

    /* Linting */
    "noUnusedLocals": true,
    "noUnusedParameters": true,
    "erasableSyntaxOnly": true,
    "noFallthroughCasesInSwitch": true
  },
  "include": ["src"]
}
</file>

<file path="tsconfig.json">
{
  "files": [],
  "references": [
    { "path": "./tsconfig.app.json" },
    { "path": "./tsconfig.node.json" }
  ]
}
</file>

<file path="tsconfig.node.json">
{
  "compilerOptions": {
    "tsBuildInfoFile": "./node_modules/.tmp/tsconfig.node.tsbuildinfo",
    "target": "es2023",
    "lib": ["ES2023"],
    "types": ["node"],
    "skipLibCheck": true,

    /* Bundler mode */
    "module": "nodenext",
    "allowImportingTsExtensions": true,
    "verbatimModuleSyntax": true,
    "moduleDetection": "force",
    "noEmit": true,

    /* Linting */
    "noUnusedLocals": true,
    "noUnusedParameters": true,
    "erasableSyntaxOnly": true,
    "noFallthroughCasesInSwitch": true
  },
  "include": ["vite.config.ts"]
}
</file>

<file path="package.json">
{
  "name": "project1",
  "private": true,
  "version": "0.0.0",
  "type": "module",
  "scripts": {
    "dev": "vite",
    "build": "tsc -b && vite build",
    "lint": "eslint .",
    "preview": "vite preview"
  },
  "dependencies": {
    "@tailwindcss/vite": "^4.3.2",
    "react": "^19.2.7",
    "react-dom": "^19.2.7",
    "tailwindcss": "^4.3.2"
  },
  "devDependencies": {
    "@eslint/js": "^10.0.1",
    "@types/node": "^24.13.2",
    "@types/react": "^19.2.17",
    "@types/react-dom": "^19.2.3",
    "@vitejs/plugin-react": "^6.0.3",
    "eslint": "^10.6.0",
    "eslint-plugin-react-hooks": "^7.1.1",
    "eslint-plugin-react-refresh": "^0.5.3",
    "globals": "^17.7.0",
    "typescript": "~6.0.2",
    "typescript-eslint": "^8.62.0",
    "vite": "^8.1.1"
  }
}
</file>

<file path="src/App.css">
@import "tailwindcss";

@theme {
  --color-black: #27272A;
  --color-grey-dark: #696969;
  --color-grey-light: #E5E7EB;
  --color-white: #FCFBFA;
  --color-lavender: #7E3AF2;
  --color-red: #E02424;
  --color-primary: #7E3AF2;
  --color-danger: #E02424;

  --font-sans: "Montserrat", system-ui, sans-serif;
  --font-montserrat: "Montserrat", sans-serif;

  --font-size-h1: 3.75rem;
  --font-size-h2: 2rem;
  --font-size-h3: 1.5rem;
  --font-size-subtitle: 1.25rem;
  --font-size-subtitle-2: 1rem;
  --font-size-body: 1.25rem;
  --font-size-body-2: 1rem;
}
</file>

<file path="src/App.tsx">
import Header from './components/Header/Header.tsx';
import './App.css'
function App() {

  return (
    <div className="w-full bg-white  mx-auto min-h-screen relative">
        <Header />
    </div>
  )
}

export default App
</file>

<file path="src/index.css">
@import "tailwindcss";
</file>

<file path="vite.config.ts">
import { defineConfig } from 'vite'
import react from '@vitejs/plugin-react'
import tailwindcss from '@tailwindcss/vite'

// https://vite.dev/config/
export default defineConfig({
  plugins: [
      react(),
      tailwindcss(),
  ],
})
</file>

</files>
